qnabot/QnABot.py
qnabot/__init__.py
qnabot/api.py
qnabot/ui.py
qnabot/tests/__init__.py
qnabot/tests/test_QnABot.py
qnabot/tests/test_api.py
qnabot/tests/test_ui.py
qnabot-0.0.6.dist-info/LICENCE
qnabot-0.0.6.dist-info/METADATA
qnabot-0.0.6.dist-info/WHEEL
qnabot-0.0.6.dist-info/top_level.txt
qnabot-0.0.6.dist-info/RECORD
