Metadata-Version: 2.1
Name: qnabot
Version: 0.0.6
Summary: Create a question answering over docs bot with one line of code.
Home-page: https://github.com/momegas/qnabot
Author: Megaklis Vasilakis
Author-email: megaklis.vasilakis@gmail.com
License: UNKNOWN
Platform: UNKNOWN
Classifier: Development Status :: 4 - Beta
License-File: LICENCE
Requires-Dist: langchain
Requires-Dist: tiktoken
Requires-Dist: unstructured
Requires-Dist: fastapi
Requires-Dist: faiss-cpu
Requires-Dist: pdfminer.six
